mc_server_interaction/__init__.py
mc_server_interaction/cli_interface.py
mc_server_interaction/exceptions.py
mc_server_interaction/interaction/__init__.py
mc_server_interaction/interaction/models.py
mc_server_interaction/interaction/property_handler.py
mc_server_interaction/interaction/server_interaction.py
mc_server_interaction/interaction/server_process.py
mc_server_interaction/interaction/utils.py
mc_server_interaction/interaction/worlds.py
mc_server_interaction/log.py
mc_server_interaction/manager/__init__.py
mc_server_interaction/manager/backup_manager.py
mc_server_interaction/manager/data_store.py
mc_server_interaction/manager/models.py
mc_server_interaction/manager/server_manager.py
mc_server_interaction/manager/utils.py
mc_server_interaction/paths.py
mc_server_interaction/utils/__init__.py
mc_server_interaction/utils/files.py
mc_server_interaction/utils/game_constants.py
mc_server_interaction/utils/singleton.py
mc_server_interaction-0.3.0.dist-info/METADATA
mc_server_interaction-0.3.0.dist-info/WHEEL
mc_server_interaction-0.3.0.dist-info/LICENSE
mc_server_interaction-0.3.0.dist-info/RECORD
